sniimapp_2.py
sniimapp2-2.1.dist-info/LICENSE
sniimapp2-2.1.dist-info/METADATA
sniimapp2-2.1.dist-info/WHEEL
sniimapp2-2.1.dist-info/top_level.txt
sniimapp2-2.1.dist-info/RECORD
