Metadata-Version: 2.1
Name: sniimapp2
Version: 2.1
Summary: Extraccion de precios SNIIM
Author-email: Rodolfo Lopez <1803672F@umich.mx>
Project-URL: Homepage, https://github.com/rodolfolopezfcca/sniimapp_2
Project-URL: Bug Tracker, https://github.com/rodolfolopezfcca/sniimapp_2
Classifier: Programming Language :: Python :: 3
Classifier: License :: OSI Approved :: MIT License
Classifier: Operating System :: OS Independent
Requires-Python: >=3.7
License-File: LICENSE
